README.md
setup.py
sensor_tracker_client/__init__.py
sensor_tracker_client/api_binder_factory.py
sensor_tracker_client/authentication.py
sensor_tracker_client/cache.py
sensor_tracker_client/connection.py
sensor_tracker_client/decorator.py
sensor_tracker_client/exceptions.py
sensor_tracker_client/response_data.py
sensor_tracker_client/sensor_tracker_client.py
sensor_tracker_client/sensor_tracker_proxy.py
sensor_tracker_client/sensor_tracker_proxy_builder.py
sensor_tracker_client/util.py
sensor_tracker_client.egg-info/PKG-INFO
sensor_tracker_client.egg-info/SOURCES.txt
sensor_tracker_client.egg-info/dependency_links.txt
sensor_tracker_client.egg-info/requires.txt
sensor_tracker_client.egg-info/top_level.txt
sensor_tracker_client.egg-info/zip-safe
sensor_tracker_client/setting/__init__.py
sensor_tracker_client/setting/basic_setting.py
sensor_tracker_client/setting/setting.py
test/__init__.py
test/api_test.py
test/connect/__init__.py
test/connect/test_connect.py
test/tools/__init__.py
test/tools/test_clone_function.py
tools/clone/__init__.py
tools/clone/platform_setup_clone.py
tools/update/__init__.py
tools/update/deployment_update.py